{"2020":{"m":{"name":"木島平村","pref":"長野県","group":"町村Ⅰ－０","pop":4579,"aging":0.38,"scale":2380525},"ind":[{"n":"財政力指数","v":0.21,"u":"-"},{"n":"経常収支比率","v":0.85,"u":"割合"},{"n":"実質公債費比率","v":0.14,"u":"割合"},{"n":"将来負担比率","v":0.26,"u":"割合"},{"n":"実質収支","v":131294.0,"u":"千円"},{"n":"実質収支比率","v":0.06,"u":"割合"}],"flow":{"歳入":{"地方税":{"t":0,"i":{"市町村民税（個人）":167463,"市町村民税（法人）":12332,"固定資産税（土地）":35745,"固定資産税（家屋）":117801,"固定資産税（償却資産）":32142,"固定資産税（交付金）":3986,"その他の税":41745}},"地方交付税":{"t":1884177,"i":{}},"地方特例交付金等":{"t":3550,"i":{}},"地方譲与税":{"t":44742,"i":{}},"国庫支出金":{"t":904392,"i":{}},"都道府県支出金":{"t":250091,"i":{}},"地方債":{"t":438027,"i":{}},"繰入金":{"t":276280,"i":{}},"その他":{"t":439112,"i":{}}},"歳出 (目的)":{"総務費":{"t":0,"i":{"総務管理費":995872,"企画費":39839,"徴税費":60391,"市町村振興費":1427,"選挙費":40499,"防災費":559}},"民生費":{"t":0,"i":{"社会福祉費":250691,"老人福祉費":378027,"児童福祉費":244945,"生活保護費":0,"災害救助費":0}},"衛生費":{"t":0,"i":{"公衆衛生費":82498,"結核対策費":0,"精神衛生費":0,"環境衛生費":56209}},"農林水産業費":{"t":0,"i":{"農業費":54741,"畜産業費":40490,"農地費":0,"林業費":430387}},"土木費":{"t":0,"i":{"土木管理費":342927,"道路橋りょう費":186437,"河川海岸費":9703,"港湾費":0,"都市計画費":34874,"住宅費":31706,"空港費":10}},"教育費":{"t":0,"i":{"教育総務費":313271,"小学校費":56680,"中学校費":63331,"高等学校費":58529,"特別支援学校費":0,"幼稚園費":0,"社会教育費":0,"保健体育費":88257,"大学費":46474}},"議会費":{"t":53232,"i":{}},"労働費":{"t":0,"i":{}},"公債費":{"t":397288,"i":{}},"その他":{"t":0,"i":{"災害復旧費":23562,"諸支出金":0,"前年度繰上充用金":0,"税関係交付金":0}}},"歳出 (性質)":{"人件費":{"t":736645,"i":{}},"扶助費":{"t":211512,"i":{}},"公債費":{"t":23562,"i":{}},"普通建設事業費":{"t":0,"i":{"補助":946142,"単独":314764,"国直轄":38613}},"物件費":{"t":636177,"i":{}},"補助費等":{"t":1227595,"i":{}},"その他":{"t":0,"i":{"災害復旧事業費":276151,"維持補修費":128137,"積立金":14522,"その他":0}}}},"stock":{"積立金":{"積立金現在高":{"財政調整基金":740563,"減債基金":58790,"その他特定目的基金":1785241}},"地方債":{"地方債現在高":{"地方債現在高(臨時財政対策債除く)":2259271,"臨時財政対策債":1409725}}},"comments":[],"grp":[{"n":"財政力指数","v":0.19,"u":"'-"},{"n":"経常収支比率","v":0.8420000000000001,"u":"割合"},{"n":"実質公債費比率","v":0.07400000000000001,"u":"割合"},{"n":"将来負担比率","v":0.0,"u":"割合"}]},"2021":{"m":{"name":"木島平村","pref":"長野県","group":"町村Ⅰ－０","pop":4508,"aging":0.37,"scale":2606604},"ind":[{"n":"財政力指数","v":0.2,"u":"-"},{"n":"経常収支比率","v":0.8,"u":"割合"},{"n":"実質公債費比率","v":0.15,"u":"割合"},{"n":"将来負担比率","v":0.04,"u":"割合"},{"n":"実質収支","v":190300.0,"u":"千円"},{"n":"実質収支比率","v":0.07,"u":"割合"}],"flow":{"歳入":{"地方税":{"t":0,"i":{"市町村民税（個人）":170488,"市町村民税（法人）":12274,"固定資産税（土地）":35356,"固定資産税（家屋）":109729,"固定資産税（償却資産）":30905,"固定資産税（交付金）":3929,"その他の税":44356}},"地方交付税":{"t":2117320,"i":{}},"地方特例交付金等":{"t":8570,"i":{}},"地方譲与税":{"t":45479,"i":{}},"国庫支出金":{"t":408603,"i":{}},"都道府県支出金":{"t":256121,"i":{}},"地方債":{"t":288238,"i":{}},"繰入金":{"t":303069,"i":{}},"その他":{"t":488483,"i":{}}},"歳出 (目的)":{"総務費":{"t":0,"i":{"総務管理費":663559,"企画費":40990,"徴税費":28316,"市町村振興費":10477,"選挙費":31200,"防災費":559}},"民生費":{"t":0,"i":{"社会福祉費":296044,"老人福祉費":196580,"児童福祉費":298262,"生活保護費":0,"災害救助費":0}},"衛生費":{"t":0,"i":{"公衆衛生費":114134,"結核対策費":0,"精神衛生費":0,"環境衛生費":65583}},"農林水産業費":{"t":0,"i":{"農業費":54968,"畜産業費":26662,"農地費":0,"林業費":346775}},"土木費":{"t":0,"i":{"土木管理費":310898,"道路橋りょう費":287498,"河川海岸費":1019,"港湾費":0,"都市計画費":34399,"住宅費":14592,"空港費":10}},"教育費":{"t":0,"i":{"教育総務費":332301,"小学校費":57298,"中学校費":39622,"高等学校費":48137,"特別支援学校費":0,"幼稚園費":0,"社会教育費":0,"保健体育費":143082,"大学費":44162}},"議会費":{"t":50318,"i":{}},"労働費":{"t":0,"i":{}},"公債費":{"t":422506,"i":{}},"その他":{"t":0,"i":{"災害復旧費":35226,"諸支出金":0,"前年度繰上充用金":0,"税関係交付金":0}}},"歳出 (性質)":{"人件費":{"t":787320,"i":{}},"扶助費":{"t":310368,"i":{}},"公債費":{"t":35226,"i":{}},"普通建設事業費":{"t":0,"i":{"補助":421236,"単独":249284,"国直轄":130907}},"物件費":{"t":506788,"i":{}},"補助費等":{"t":634977,"i":{}},"その他":{"t":0,"i":{"災害復旧事業費":118377,"維持補修費":201790,"積立金":8248,"その他":0}}}},"stock":{"積立金":{"積立金現在高":{"財政調整基金":890409,"減債基金":82541,"その他特定目的基金":1754817}},"地方債":{"地方債現在高":{"地方債現在高(臨時財政対策債除く)":2191368,"臨時財政対策債":1353268}}},"comments":[],"grp":[{"n":"財政力指数","v":0.2,"u":"'-"},{"n":"経常収支比率","v":0.794,"u":"割合"},{"n":"実質公債費比率","v":0.075,"u":"割合"},{"n":"将来負担比率","v":0.0,"u":"割合"}]},"2022":{"m":{"name":"木島平村","pref":"長野県","group":"町村Ⅰ－０","pop":4438,"aging":0.39,"scale":2552954},"ind":[{"n":"財政力指数","v":0.2,"u":"-"},{"n":"経常収支比率","v":0.83,"u":"割合"},{"n":"実質公債費比率","v":0.14,"u":"割合"},{"n":"実質収支","v":181527.0,"u":"千円"},{"n":"実質収支比率","v":0.07,"u":"割合"}],"flow":{"歳入":{"地方税":{"t":0,"i":{"市町村民税（個人）":171850,"市町村民税（法人）":12544,"固定資産税（土地）":34818,"固定資産税（家屋）":115620,"固定資産税（償却資産）":35357,"固定資産税（交付金）":3929,"その他の税":45478}},"地方交付税":{"t":2142252,"i":{}},"地方特例交付金等":{"t":2095,"i":{}},"地方譲与税":{"t":46508,"i":{}},"国庫支出金":{"t":373049,"i":{}},"都道府県支出金":{"t":243116,"i":{}},"地方債":{"t":179580,"i":{}},"繰入金":{"t":366427,"i":{}},"その他":{"t":559643,"i":{}}},"歳出 (目的)":{"総務費":{"t":0,"i":{"総務管理費":654257,"企画費":64455,"徴税費":47284,"市町村振興費":16125,"選挙費":36871,"防災費":656}},"民生費":{"t":0,"i":{"社会福祉費":304400,"老人福祉費":184704,"児童福祉費":261520,"生活保護費":0,"災害救助費":0}},"衛生費":{"t":0,"i":{"公衆衛生費":105297,"結核対策費":0,"精神衛生費":0,"環境衛生費":72662}},"農林水産業費":{"t":0,"i":{"農業費":55218,"畜産業費":28430,"農地費":0,"林業費":459423}},"土木費":{"t":0,"i":{"土木管理費":347598,"道路橋りょう費":189221,"河川海岸費":3341,"港湾費":0,"都市計画費":29378,"住宅費":12448,"空港費":10}},"教育費":{"t":0,"i":{"教育総務費":296555,"小学校費":66261,"中学校費":40898,"高等学校費":47994,"特別支援学校費":0,"幼稚園費":0,"社会教育費":0,"保健体育費":87448,"大学費":53954}},"議会費":{"t":48064,"i":{}},"労働費":{"t":0,"i":{}},"公債費":{"t":436888,"i":{}},"その他":{"t":0,"i":{"災害復旧費":11796,"諸支出金":0,"前年度繰上充用金":0,"税関係交付金":0}}},"歳出 (性質)":{"人件費":{"t":794533,"i":{}},"扶助費":{"t":266670,"i":{}},"公債費":{"t":11796,"i":{}},"普通建設事業費":{"t":0,"i":{"補助":494613,"単独":160089,"国直轄":13914}},"物件費":{"t":617125,"i":{}},"補助費等":{"t":729948,"i":{}},"その他":{"t":0,"i":{"災害復旧事業費":144991,"維持補修費":141356,"積立金":0,"その他":0}}}},"stock":{"積立金":{"積立金現在高":{"財政調整基金":991991,"減債基金":82775,"その他特定目的基金":1732467}},"地方債":{"地方債現在高":{"地方債現在高(臨時財政対策債除く)":2063832,"臨時財政対策債":1232300}}},"comments":[],"grp":[{"n":"財政力指数","v":0.19,"u":"'-"},{"n":"経常収支比率","v":0.83,"u":"割合"},{"n":"実質公債費比率","v":0.075,"u":"割合"},{"n":"将来負担比率","v":0.0,"u":"割合"}]},"2023":{"m":{"name":"木島平村","pref":"長野県","group":"町村Ⅰ－０","pop":4364,"aging":0.4,"scale":2562809},"ind":[{"n":"財政力指数","v":0.19,"u":"-"},{"n":"経常収支比率","v":0.81,"u":"割合"},{"n":"実質公債費比率","v":0.13,"u":"割合"},{"n":"実質収支","v":168390.0,"u":"千円"},{"n":"実質収支比率","v":0.07,"u":"割合"}],"flow":{"歳入":{"地方税":{"t":0,"i":{"市町村民税（個人）":175428,"市町村民税（法人）":12990,"固定資産税（土地）":34360,"固定資産税（家屋）":117148,"固定資産税（償却資産）":36560,"固定資産税（交付金）":3929,"その他の税":44863}},"地方交付税":{"t":2144782,"i":{}},"地方特例交付金等":{"t":2015,"i":{}},"地方譲与税":{"t":46845,"i":{}},"国庫支出金":{"t":248821,"i":{}},"都道府県支出金":{"t":212173,"i":{}},"地方債":{"t":282051,"i":{}},"繰入金":{"t":625664,"i":{}},"その他":{"t":448843,"i":{}}},"歳出 (目的)":{"総務費":{"t":0,"i":{"総務管理費":900266,"企画費":41081,"徴税費":29878,"市町村振興費":3933,"選挙費":29410,"防災費":702}},"民生費":{"t":0,"i":{"社会福祉費":326525,"老人福祉費":186086,"児童福祉費":253469,"生活保護費":0,"災害救助費":511}},"衛生費":{"t":0,"i":{"公衆衛生費":104383,"結核対策費":0,"精神衛生費":0,"環境衛生費":74006}},"農林水産業費":{"t":0,"i":{"農業費":36091,"畜産業費":51857,"農地費":0,"林業費":205658}},"土木費":{"t":0,"i":{"土木管理費":82903,"道路橋りょう費":210981,"河川海岸費":1067,"港湾費":0,"都市計画費":276215,"住宅費":22133,"空港費":10}},"教育費":{"t":0,"i":{"教育総務費":411550,"小学校費":81478,"中学校費":40347,"高等学校費":133453,"特別支援学校費":0,"幼稚園費":0,"社会教育費":0,"保健体育費":106979,"大学費":49293}},"議会費":{"t":45316,"i":{}},"労働費":{"t":0,"i":{}},"公債費":{"t":520422,"i":{}},"その他":{"t":0,"i":{"災害復旧費":4906,"諸支出金":0,"前年度繰上充用金":0,"税関係交付金":0}}},"歳出 (性質)":{"人件費":{"t":764390,"i":{}},"扶助費":{"t":214367,"i":{}},"公債費":{"t":4906,"i":{}},"普通建設事業費":{"t":0,"i":{"補助":664989,"単独":325466,"国直轄":40666}},"物件費":{"t":520210,"i":{}},"補助費等":{"t":915618,"i":{}},"その他":{"t":0,"i":{"災害復旧事業費":284300,"維持補修費":136273,"積立金":0,"その他":0}}}},"stock":{"積立金":{"積立金現在高":{"財政調整基金":993464,"減債基金":182396,"その他特定目的基金":1734083}},"地方債":{"地方債現在高":{"地方債現在高(臨時財政対策債除く)":2045093,"臨時財政対策債":1020522}}},"comments":[],"grp":[{"n":"財政力指数","v":0.18,"u":"'-"},{"n":"経常収支比率","v":0.8420000000000001,"u":"割合"},{"n":"実質公債費比率","v":0.077,"u":"割合"},{"n":"将来負担比率","v":0.0,"u":"割合"}]},"2024":{"m":{"name":"木島平村","pref":"長野県","group":"町村Ⅰ－０","pop":4237,"aging":0.4,"scale":2561614},"ind":[{"n":"財政力指数","v":0.2,"u":"-"},{"n":"経常収支比率","v":0.82,"u":"割合"},{"n":"実質公債費比率","v":0.11,"u":"割合"},{"n":"実質収支","v":161446.0,"u":"千円"},{"n":"実質収支比率","v":0.06,"u":"割合"}],"flow":{"歳入":{"地方税":{"t":0,"i":{"市町村民税（個人）":155779,"市町村民税（法人）":11960,"固定資産税（土地）":35165,"固定資産税（家屋）":120441,"固定資産税（償却資産）":39292,"固定資産税（交付金）":3929,"その他の税":45197}},"地方交付税":{"t":2154060,"i":{}},"地方特例交付金等":{"t":20269,"i":{}},"地方譲与税":{"t":49051,"i":{}},"国庫支出金":{"t":271733,"i":{}},"都道府県支出金":{"t":204253,"i":{}},"地方債":{"t":204109,"i":{}},"繰入金":{"t":441073,"i":{}},"その他":{"t":510161,"i":{}}},"歳出 (目的)":{"総務費":{"t":0,"i":{"総務管理費":676944,"企画費":109326,"徴税費":74480,"市町村振興費":5986,"選挙費":29718,"防災費":653}},"民生費":{"t":0,"i":{"社会福祉費":292044,"老人福祉費":199602,"児童福祉費":259487,"生活保護費":0,"災害救助費":267}},"衛生費":{"t":0,"i":{"公衆衛生費":95585,"結核対策費":0,"精神衛生費":0,"環境衛生費":68317}},"農林水産業費":{"t":0,"i":{"農業費":44901,"畜産業費":40932,"農地費":0,"林業費":180964}},"土木費":{"t":0,"i":{"土木管理費":65500,"道路橋りょう費":229348,"河川海岸費":1153,"港湾費":0,"都市計画費":235226,"住宅費":14023,"空港費":10}},"教育費":{"t":0,"i":{"教育総務費":384400,"小学校費":79067,"中学校費":75939,"高等学校費":76189,"特別支援学校費":0,"幼稚園費":0,"社会教育費":0,"保健体育費":99572,"大学費":53633}},"議会費":{"t":48173,"i":{}},"労働費":{"t":0,"i":{}},"公債費":{"t":537733,"i":{}},"その他":{"t":0,"i":{"災害復旧費":2200,"諸支出金":0,"前年度繰上充用金":0,"税関係交付金":0}}},"歳出 (性質)":{"人件費":{"t":801911,"i":{}},"扶助費":{"t":248357,"i":{}},"公債費":{"t":2200,"i":{}},"普通建設事業費":{"t":0,"i":{"補助":630851,"単独":175936,"国直轄":17508}},"物件費":{"t":593196,"i":{}},"補助費等":{"t":896261,"i":{}},"その他":{"t":0,"i":{"災害復旧事業費":147480,"維持補修費":202297,"積立金":0,"その他":0}}}},"stock":{"積立金":{"積立金現在高":{"財政調整基金":994761,"減債基金":165324,"その他特定目的基金":1790751}},"地方債":{"地方債現在高":{"地方債現在高(臨時財政対策債除く)":1975486,"臨時財政対策債":764495}}},"comments":[{"label":"経常収支比率","text":"令和6年度の経常収支比率は82.4％となり、前年度よりも1.3ポイント増となりました。経常的支出が35,676千円増加（人件費、物件費等）したことと、経常的な一般財源収入が6,552千円増加した（普通交付税の増等）ことによるものです。"},{"label":"歳出 (性質別)","text":"歳出決算額は、住民1人あたり1,004,602円となっています。主な構成項目は、補助費等211,532円、次いで人件費189,264円、物件費140,004円、公債費126,914円となっています。\n　前年度と比較すると、人件費、物件費の伸びが大きく、普通建設事業、積立金が減少となりました。主な要因は、人件費については、会計年度任用職員の勤勉手当支給、物件費については、物価高や委託料の増額によるものです。\n　毎年度、ローリングにより見直しを行う実施計画において、長期計画を定めるとともに、公共施設の適正管理に努め、普通建設費等の抑制や平準化に努めることとします。"},{"label":"歳出 (目的別)","text":"目的別の住民一人当たりの経費については、類似団体平均と比較し、全ての項目で下回っています。\n　類似団体平均と比較して、消防費、公債費が年々上昇傾向にありますが、衛生費は非常に低い水準となっております。"},{"label":"財政力指数","text":"令和6年度の財政力指数は0.20となり、前年度より0.01ポイント増となりました。本村の財政力指数は、概ね横ばいとなっており、今後も少子高齢化の進展、人口減少により所得の伸びは期待できず、同様の傾向が続くものと思われます。　　　　　　　　　　　\n　類似団体の順位は50位であるものの、今後の財政力強化のため、基幹産業である農業の生産性向上や高付加価値を高めるなど、村民所得向上の後押しを進めていく必要があります。"},{"label":"実質公債費比率","text":"令和6年度の実質公債費率は、前年度比2.2ポイント減の11.0となりました。標準財政規模が1,195千円減少しましたが、元利償還金と準元利償還金の合計額が122,473千円減少したため。単年度の数値としては、3.5ポイント減少しましたが、3年間の平均値で比較すると2.2ポイント減少する結果となりました。\n　類似団体順位は、151中131位、全国平均、長野県平均と比較しても非常に高い数値となっており、普通建設事業と地方債の新規発行額の抑制に努める必要があります。"},{"label":"将来負担比率","text":"令和6年度の将来負担率は、ゼロとなっています。主な要因は地方債現在高（未償還元金）などの将来負担額が減少した一方、充当可能財源である基金残高が増加したことによるものです。"},{"label":"積立金現在高","text":"（増減理由）\n　基金全体の令和6年度末残高は、前年比40,892千円増の2,950,836千円となりました。\n　取崩額は441,073千円で、主なものは財政調整基金241,643千円、減債基金159,027千円、ふるさとづくり基金39,000千円などです。\n　積立金は481,965千円で、主なものは財政調整基金242,940千円、減債基金51,955千円、ふるさとづくり基金88,406千円などです。\n（今後の方針）\n　今後も普通建設事業の支出とともに公共施設基金の取崩しが予定されていますが、毎年ローリングにより見直しを行う実施計画において、長期計画を定めるとともに、公共施設の適正管理を行い、普通建設事業費の平準化、地方債新規発行額の抑制、基金の取崩しの抑制に努めています。"}],"grp":[{"n":"財政力指数","v":0.18,"u":"'-"},{"n":"経常収支比率","v":0.853,"u":"割合"},{"n":"実質公債費比率","v":0.08,"u":"割合"},{"n":"将来負担比率","v":0.0,"u":"割合"}]}}