{"2020":{"m":{"name":"飛島村","pref":"愛知県","group":"町村Ⅰ－１","pop":4791,"aging":0.28,"scale":4601872},"ind":[{"n":"財政力指数","v":2.21,"u":"-"},{"n":"経常収支比率","v":0.68,"u":"割合"},{"n":"実質公債費比率","v":-0.01,"u":"割合"},{"n":"実質収支","v":390777.0,"u":"千円"},{"n":"実質収支比率","v":0.08,"u":"割合"}],"flow":{"歳入":{"地方税":{"t":0,"i":{"市町村民税（個人）":298217,"市町村民税（法人）":561789,"固定資産税（土地）":1553065,"固定資産税（家屋）":1068373,"固定資産税（償却資産）":457580,"固定資産税（交付金）":97152,"その他の税":95186}},"地方交付税":{"t":9155,"i":{}},"地方特例交付金等":{"t":10862,"i":{}},"地方譲与税":{"t":234735,"i":{}},"国庫支出金":{"t":795521,"i":{}},"都道府県支出金":{"t":164679,"i":{}},"地方債":{"t":0,"i":{}},"繰入金":{"t":340189,"i":{}},"その他":{"t":1385026,"i":{}}},"歳出 (目的)":{"総務費":{"t":0,"i":{"総務管理費":2556662,"企画費":112251,"徴税費":34568,"市町村振興費":1026,"選挙費":2626,"防災費":755}},"民生費":{"t":0,"i":{"社会福祉費":358567,"老人福祉費":352117,"児童福祉費":502561,"生活保護費":0,"災害救助費":0}},"衛生費":{"t":0,"i":{"公衆衛生費":297909,"結核対策費":0,"精神衛生費":0,"環境衛生費":164389}},"農林水産業費":{"t":0,"i":{"農業費":379919,"畜産業費":0,"農地費":0,"林業費":51757}},"土木費":{"t":0,"i":{"土木管理費":88864,"道路橋りょう費":473119,"河川海岸費":124,"港湾費":0,"都市計画費":40509,"住宅費":0,"空港費":0}},"教育費":{"t":0,"i":{"教育総務費":512068,"小学校費":123245,"中学校費":62825,"高等学校費":33231,"特別支援学校費":0,"幼稚園費":0,"社会教育費":0,"保健体育費":265905,"大学費":26862}},"議会費":{"t":88182,"i":{}},"労働費":{"t":21540,"i":{}},"公債費":{"t":12847,"i":{}},"その他":{"t":0,"i":{"災害復旧費":0,"諸支出金":0,"前年度繰上充用金":0,"税関係交付金":0}}},"歳出 (性質)":{"人件費":{"t":1036575,"i":{}},"扶助費":{"t":420688,"i":{}},"公債費":{"t":0,"i":{}},"普通建設事業費":{"t":0,"i":{"補助":1062117,"単独":1270102,"国直轄":58967}},"物件費":{"t":1039264,"i":{}},"補助費等":{"t":1504522,"i":{}},"その他":{"t":0,"i":{"災害復旧事業費":1027584,"維持補修費":31590,"積立金":0,"その他":0}}}},"stock":{"積立金":{"積立金現在高":{"財政調整基金":900000,"減債基金":28329,"その他特定目的基金":6958512}},"地方債":{"地方債現在高":{"地方債現在高(臨時財政対策債除く)":137468,"臨時財政対策債":0}}},"comments":[],"grp":[{"n":"財政力指数","v":0.29,"u":"'-"},{"n":"経常収支比率","v":0.833,"u":"割合"},{"n":"実質公債費比率","v":0.057999999999999996,"u":"割合"},{"n":"将来負担比率","v":0.0,"u":"割合"}]},"2021":{"m":{"name":"飛島村","pref":"愛知県","group":"町村Ⅰ－１","pop":4706,"aging":0.29,"scale":4433179},"ind":[{"n":"財政力指数","v":2.1,"u":"-"},{"n":"経常収支比率","v":0.74,"u":"割合"},{"n":"実質公債費比率","v":-0.01,"u":"割合"},{"n":"実質収支","v":369762.0,"u":"千円"},{"n":"実質収支比率","v":0.08,"u":"割合"}],"flow":{"歳入":{"地方税":{"t":0,"i":{"市町村民税（個人）":299565,"市町村民税（法人）":409918,"固定資産税（土地）":1532148,"固定資産税（家屋）":1005799,"固定資産税（償却資産）":431329,"固定資産税（交付金）":105264,"その他の税":109572}},"地方交付税":{"t":8926,"i":{}},"地方特例交付金等":{"t":80962,"i":{}},"地方譲与税":{"t":228829,"i":{}},"国庫支出金":{"t":459084,"i":{}},"都道府県支出金":{"t":158894,"i":{}},"地方債":{"t":0,"i":{}},"繰入金":{"t":672216,"i":{}},"その他":{"t":960165,"i":{}}},"歳出 (目的)":{"総務費":{"t":0,"i":{"総務管理費":997450,"企画費":113229,"徴税費":22829,"市町村振興費":5429,"選挙費":358,"防災費":863}},"民生費":{"t":0,"i":{"社会福祉費":399936,"老人福祉費":360904,"児童福祉費":910813,"生活保護費":0,"災害救助費":0}},"衛生費":{"t":0,"i":{"公衆衛生費":357790,"結核対策費":0,"精神衛生費":0,"環境衛生費":161430}},"農林水産業費":{"t":0,"i":{"農業費":383538,"畜産業費":0,"農地費":0,"林業費":38877}},"土木費":{"t":0,"i":{"土木管理費":161484,"道路橋りょう費":381733,"河川海岸費":119,"港湾費":0,"都市計画費":30837,"住宅費":14071,"空港費":0}},"教育費":{"t":0,"i":{"教育総務費":625179,"小学校費":172232,"中学校費":65454,"高等学校費":36003,"特別支援学校費":0,"幼稚園費":0,"社会教育費":0,"保健体育費":325601,"大学費":25889}},"議会費":{"t":90946,"i":{}},"労働費":{"t":21819,"i":{}},"公債費":{"t":20197,"i":{}},"その他":{"t":0,"i":{"災害復旧費":0,"諸支出金":0,"前年度繰上充用金":0,"税関係交付金":0}}},"歳出 (性質)":{"人件費":{"t":1051641,"i":{}},"扶助費":{"t":523363,"i":{}},"公債費":{"t":0,"i":{}},"普通建設事業費":{"t":0,"i":{"補助":607520,"単独":1397791,"国直轄":224068}},"物件費":{"t":1145532,"i":{}},"補助費等":{"t":1032798,"i":{}},"その他":{"t":0,"i":{"災害復旧事業費":1053919,"維持補修費":40901,"積立金":0,"その他":0}}}},"stock":{"積立金":{"積立金現在高":{"財政調整基金":900000,"減債基金":28386,"その他特定目的基金":6577696}},"地方債":{"地方債現在高":{"地方債現在高(臨時財政対策債除く)":117648,"臨時財政対策債":0}}},"comments":[],"grp":[{"n":"財政力指数","v":0.27,"u":"'-"},{"n":"経常収支比率","v":0.7829999999999999,"u":"割合"},{"n":"実質公債費比率","v":0.061,"u":"割合"},{"n":"将来負担比率","v":0.0,"u":"割合"}]},"2022":{"m":{"name":"飛島村","pref":"愛知県","group":"町村Ⅰ－１","pop":4657,"aging":0.29,"scale":4771035},"ind":[{"n":"財政力指数","v":2.02,"u":"-"},{"n":"経常収支比率","v":0.69,"u":"割合"},{"n":"実質公債費比率","v":-0.01,"u":"割合"},{"n":"実質収支","v":379497.0,"u":"千円"},{"n":"実質収支比率","v":0.08,"u":"割合"}],"flow":{"歳入":{"地方税":{"t":0,"i":{"市町村民税（個人）":298612,"市町村民税（法人）":494578,"固定資産税（土地）":1531686,"固定資産税（家屋）":1053929,"固定資産税（償却資産）":760329,"固定資産税（交付金）":104063,"その他の税":116235}},"地方交付税":{"t":8957,"i":{}},"地方特例交付金等":{"t":9826,"i":{}},"地方譲与税":{"t":231303,"i":{}},"国庫支出金":{"t":415192,"i":{}},"都道府県支出金":{"t":184349,"i":{}},"地方債":{"t":0,"i":{}},"繰入金":{"t":426587,"i":{}},"その他":{"t":1192768,"i":{}}},"歳出 (目的)":{"総務費":{"t":0,"i":{"総務管理費":971700,"企画費":136863,"徴税費":32229,"市町村振興費":12398,"選挙費":108,"防災費":809}},"民生費":{"t":0,"i":{"社会福祉費":393647,"老人福祉費":323227,"児童福祉費":452567,"生活保護費":0,"災害救助費":0}},"衛生費":{"t":0,"i":{"公衆衛生費":406275,"結核対策費":0,"精神衛生費":0,"環境衛生費":205925}},"農林水産業費":{"t":0,"i":{"農業費":374323,"畜産業費":0,"農地費":0,"林業費":43321}},"土木費":{"t":0,"i":{"土木管理費":72484,"道路橋りょう費":232143,"河川海岸費":3693,"港湾費":0,"都市計画費":31545,"住宅費":5480,"空港費":0}},"教育費":{"t":0,"i":{"教育総務費":1780598,"小学校費":180904,"中学校費":64345,"高等学校費":30906,"特別支援学校費":0,"幼稚園費":0,"社会教育費":0,"保健体育費":1478247,"大学費":26196}},"議会費":{"t":92722,"i":{}},"労働費":{"t":21840,"i":{}},"公債費":{"t":7468,"i":{}},"その他":{"t":0,"i":{"災害復旧費":0,"諸支出金":0,"前年度繰上充用金":0,"税関係交付金":0}}},"歳出 (性質)":{"人件費":{"t":1092927,"i":{}},"扶助費":{"t":436572,"i":{}},"公債費":{"t":0,"i":{}},"普通建設事業費":{"t":0,"i":{"補助":626893,"単独":2036306,"国直轄":333170}},"物件費":{"t":1284012,"i":{}},"補助費等":{"t":1037872,"i":{}},"その他":{"t":0,"i":{"災害復旧事業費":1579917,"維持補修費":30884,"積立金":0,"その他":0}}}},"stock":{"積立金":{"積立金現在高":{"財政調整基金":900000,"減債基金":28429,"その他特定目的基金":6352446}},"地方債":{"地方債現在高":{"地方債現在高(臨時財政対策債除く)":110296,"臨時財政対策債":0}}},"comments":[],"grp":[{"n":"財政力指数","v":0.26,"u":"'-"},{"n":"経常収支比率","v":0.816,"u":"割合"},{"n":"実質公債費比率","v":0.064,"u":"割合"},{"n":"将来負担比率","v":0.0,"u":"割合"}]},"2023":{"m":{"name":"飛島村","pref":"愛知県","group":"町村Ⅰ－１","pop":4711,"aging":0.29,"scale":4607500},"ind":[{"n":"財政力指数","v":1.94,"u":"-"},{"n":"経常収支比率","v":0.75,"u":"割合"},{"n":"実質公債費比率","v":-0.01,"u":"割合"},{"n":"実質収支","v":291744.0,"u":"千円"},{"n":"実質収支比率","v":0.06,"u":"割合"}],"flow":{"歳入":{"地方税":{"t":0,"i":{"市町村民税（個人）":314495,"市町村民税（法人）":486735,"固定資産税（土地）":1534147,"固定資産税（家屋）":1063387,"固定資産税（償却資産）":457079,"固定資産税（交付金）":102430,"その他の税":118674}},"地方交付税":{"t":7166,"i":{}},"地方特例交付金等":{"t":16763,"i":{}},"地方譲与税":{"t":223731,"i":{}},"国庫支出金":{"t":247654,"i":{}},"都道府県支出金":{"t":162403,"i":{}},"地方債":{"t":0,"i":{}},"繰入金":{"t":193604,"i":{}},"その他":{"t":925271,"i":{}}},"歳出 (目的)":{"総務費":{"t":0,"i":{"総務管理費":1606544,"企画費":114084,"徴税費":34168,"市町村振興費":7212,"選挙費":91,"防災費":823}},"民生費":{"t":0,"i":{"社会福祉費":424335,"老人福祉費":346379,"児童福祉費":446953,"生活保護費":0,"災害救助費":0}},"衛生費":{"t":0,"i":{"公衆衛生費":366851,"結核対策費":0,"精神衛生費":0,"環境衛生費":178531}},"農林水産業費":{"t":0,"i":{"農業費":346604,"畜産業費":0,"農地費":0,"林業費":42277}},"土木費":{"t":0,"i":{"土木管理費":79496,"道路橋りょう費":182394,"河川海岸費":39586,"港湾費":0,"都市計画費":30750,"住宅費":12221,"空港費":0}},"教育費":{"t":0,"i":{"教育総務費":645478,"小学校費":177398,"中学校費":72287,"高等学校費":41002,"特別支援学校費":0,"幼稚園費":0,"社会教育費":0,"保健体育費":327018,"大学費":27773}},"議会費":{"t":93162,"i":{}},"労働費":{"t":22062,"i":{}},"公債費":{"t":7460,"i":{}},"その他":{"t":0,"i":{"災害復旧費":0,"諸支出金":0,"前年度繰上充用金":0,"税関係交付金":0}}},"歳出 (性質)":{"人件費":{"t":1104489,"i":{}},"扶助費":{"t":438034,"i":{}},"公債費":{"t":0,"i":{}},"普通建設事業費":{"t":0,"i":{"補助":835809,"単独":463965,"国直轄":5715}},"物件費":{"t":1270567,"i":{}},"補助費等":{"t":1228185,"i":{}},"その他":{"t":0,"i":{"災害復旧事業費":393344,"維持補修費":34304,"積立金":0,"その他":0}}}},"stock":{"積立金":{"積立金現在高":{"財政調整基金":900000,"減債基金":28473,"その他特定目的基金":6979444}},"地方債":{"地方債現在高":{"地方債現在高(臨時財政対策債除く)":102944,"臨時財政対策債":0}}},"comments":[],"grp":[{"n":"財政力指数","v":0.26,"u":"'-"},{"n":"経常収支比率","v":0.8340000000000001,"u":"割合"},{"n":"実質公債費比率","v":0.067,"u":"割合"},{"n":"将来負担比率","v":0.0,"u":"割合"}]},"2024":{"m":{"name":"飛島村","pref":"愛知県","group":"町村Ⅰ－１","pop":4713,"aging":0.29,"scale":4872371},"ind":[{"n":"財政力指数","v":1.99,"u":"-"},{"n":"経常収支比率","v":0.74,"u":"割合"},{"n":"実質公債費比率","v":-0.01,"u":"割合"},{"n":"実質収支","v":334150.0,"u":"千円"},{"n":"実質収支比率","v":0.07,"u":"割合"}],"flow":{"歳入":{"地方税":{"t":0,"i":{"市町村民税（個人）":289827,"市町村民税（法人）":655461,"固定資産税（土地）":1651779,"固定資産税（家屋）":1132028,"固定資産税（償却資産）":460016,"固定資産税（交付金）":108639,"その他の税":118318}},"地方交付税":{"t":5642,"i":{}},"地方特例交付金等":{"t":35769,"i":{}},"地方譲与税":{"t":231402,"i":{}},"国庫支出金":{"t":279931,"i":{}},"都道府県支出金":{"t":189210,"i":{}},"地方債":{"t":0,"i":{}},"繰入金":{"t":223538,"i":{}},"その他":{"t":1054114,"i":{}}},"歳出 (目的)":{"総務費":{"t":0,"i":{"総務管理費":1355018,"企画費":120572,"徴税費":35932,"市町村振興費":9273,"選挙費":1858,"防災費":848}},"民生費":{"t":0,"i":{"社会福祉費":524187,"老人福祉費":373479,"児童福祉費":488271,"生活保護費":0,"災害救助費":0}},"衛生費":{"t":0,"i":{"公衆衛生費":721595,"結核対策費":0,"精神衛生費":0,"環境衛生費":301397}},"農林水産業費":{"t":0,"i":{"農業費":302948,"畜産業費":0,"農地費":0,"林業費":45076}},"土木費":{"t":0,"i":{"土木管理費":80837,"道路橋りょう費":206158,"河川海岸費":105,"港湾費":0,"都市計画費":76422,"住宅費":158606,"空港費":0}},"教育費":{"t":0,"i":{"教育総務費":650351,"小学校費":168985,"中学校費":78511,"高等学校費":47062,"特別支援学校費":0,"幼稚園費":0,"社会教育費":0,"保健体育費":327207,"大学費":28586}},"議会費":{"t":94125,"i":{}},"労働費":{"t":25221,"i":{}},"公債費":{"t":7453,"i":{}},"その他":{"t":0,"i":{"災害復旧費":0,"諸支出金":0,"前年度繰上充用金":0,"税関係交付金":0}}},"歳出 (性質)":{"人件費":{"t":1172299,"i":{}},"扶助費":{"t":496483,"i":{}},"公債費":{"t":0,"i":{}},"普通建設事業費":{"t":0,"i":{"補助":762281,"単独":863843,"国直轄":2897}},"物件費":{"t":1402113,"i":{}},"補助費等":{"t":1228903,"i":{}},"その他":{"t":0,"i":{"災害復旧事業費":816393,"維持補修費":35169,"積立金":0,"その他":0}}}},"stock":{"積立金":{"積立金現在高":{"財政調整基金":900000,"減債基金":28527,"その他特定目的基金":7259517}},"地方債":{"地方債現在高":{"地方債現在高(臨時財政対策債除く)":95592,"臨時財政対策債":0}}},"comments":[{"label":"経常収支比率","text":"令和３年度は、分母である経常一般財源等のうち、新型コロナウイルス感染症の影響により地方税が減少したことに加え、分子である経常経費充当一般財源等のうち、主に物件費が増加したことにより、数値が悪化した。\n　令和４年度は、地方税の増加（固定資産税（償却資産）における新設大規模償却資産の課税定額増額分）に伴い数値が改善したが、この増加分は単年度限りのものであるため、令和５年度及び令和６年度は、再び令和３年度と同水準となった。\n　類似団体と比較しても優良な水準を維持しているが、将来にわたり持続可能な行財政運営を確立するため、さらなる経常経費の削減に努める。"},{"label":"歳出 (性質別)","text":"類似団体と比較すると、人件費、物件費、扶助費、補助費等、積立金及び貸付金が高い数値となっている。\n人件費：人口規模に比して取り扱う行政事務が多いため、どうしても住民１人当たりのコストが高くなる。今後も、条例で定められる定員管理を遵守しつつ、住民サービスの水準を維持するよう努める。\n物件費：人口規模に比して公共施設の保有量が多いため、これにかかる維持管理費が増加していることが要因のひとつとなっている。今後は、さらなる行財政改革を進め、施設の維持管理費を削減するほか、インソースの流れを重視し、委託費総額の圧縮に努める。\n扶助費：令和２年度から令和６年度は、新型コロナウイルス又は物価高騰対応事業により各種給付金事業を実施しているため増加傾向にある。それ以外の扶助費は横ばいで推移している。\n補助費等：令和５年度から飛島学園の給食費無償化を実施しているため増加している。類似団体と比べて高くなっているのは、一部事務組合への負担金によるところが大きい。小規模自治体としては、事務の共同運営は不可欠だが、一部事務組合の負担金が過大とならないように、今後も注視していく。\n積立金：普通建設事業費の増減により積立金も増減が左右される。令和６年度は、普通建設事業費が増加したため、その財源としている地域整備基金積立額が減少した。\n貸付金：令和６年度から新規住宅地開発のため宅地造成事業特別会計を設置した。令和８年度まで宅地造成工事が実施されるため、令和９年度以降は令和５年度の水準に戻る予定である。"},{"label":"歳出 (目的別)","text":"類似団体と比較すると、議会費、民生費、衛生費、労働費及び消防費が高い数値となっている。\n議会費：これまで大きな増減はないものの、主に物件費が類似団体と比べて高いため、類似団体に比して高い水準で推移している。\n民生費：令和３年度は、第一保育所大規模改修工事を実施したため多額となっている。令和６年度は、国民健康保険特別会計繰出金の増、定額減税補足給付金（調整給付）給付事業により増加した。\n衛生費：令和６年度は、聖苑大規模改修工事、南部エコプラザ整備工事実施設計委託、北部エコプラザ整備工事により大きく増加した。\n労働費：シルバー人材センターへの補助金であり、人件費の高騰により年々増加傾向にある。\n消防費：令和４年度は、梅之郷地区津波一時避難所建設工事（繰越事業）により多額となっている。避難所整備は一通り完了したため、今後は平準化していく見込みである。"},{"label":"財政力指数","text":"基準財政需要額は、人口の増減が少ないことに加え、地方債の発行を抑制しているため、ほぼ横ばいで推移してたが、令和３年度以降は国勢調査人口の増や普通交付税の再算定に伴い増加している。\n　基準財政収入額は、臨海部に立地する企業からの固定資産税等収入により、類似団体を大きく上回る数値であり増加している。\n　財政力指数は、令和２年度以降において基準財政収入額よりも基準財政需要額の増額が大きいため低下傾向となっている。"},{"label":"実質公債費比率","text":"これまで地方債発行を抑制してきたため、地方債の元利償還金等が普通地方交付税に係る基準財政需要額算入を下回り、過去から数値がマイナスとなっている。\n　令和３年度から、すこやかセンター整備事業のため、平成29年度に発行した地方債の元金の償還が始まったことにより数値が低下した。"},{"label":"将来負担比率","text":"過去からの地方債発行の抑制等により、将来負担額が充当可能財源等を大きく下回っているため、将来負担比率の数値はゼロとなっている。\n　今後の財政運営においても、将来世代に応分の負担を考慮しつつ、財政の健全化に努める。"},{"label":"積立金現在高","text":"（増減理由）\n・令和６年度の基金残高は、普通会計で約81.2億円となっており、前年度から約2.8億円の増加となっている。\n・これは、令和６年度は比較的多額の費用を要する事業がなかったことにより、特定目的基金である地域整備基金を約2.8億円積み立てることができたためである。\n・それ以外の基金は横ばいである。\n（今後の方針）\n・令和９年度以降に第５次総合計画に掲げている主要施策による整備費等により取り崩しが見込まれる。それまでは、横ばいから微増を見込んでいる。"}],"grp":[{"n":"財政力指数","v":0.27,"u":"'-"},{"n":"経常収支比率","v":0.8420000000000001,"u":"割合"},{"n":"実質公債費比率","v":0.066,"u":"割合"},{"n":"将来負担比率","v":0.0,"u":"割合"}]}}